LICENSE
MANIFEST.in
README.rst
setup.cfg
setup.py
sqlalchemy_nuodb/__init__.py
sqlalchemy_nuodb/base.py
sqlalchemy_nuodb/pynuodb.py
sqlalchemy_nuodb/requirements.py
sqlalchemy_nuodb.egg-info/PKG-INFO
sqlalchemy_nuodb.egg-info/SOURCES.txt
sqlalchemy_nuodb.egg-info/dependency_links.txt
sqlalchemy_nuodb.egg-info/entry_points.txt
sqlalchemy_nuodb.egg-info/not-zip-safe
sqlalchemy_nuodb.egg-info/requires.txt
sqlalchemy_nuodb.egg-info/top_level.txt