Metadata-Version: 1.1
Name: sqlalchemy-nuodb
Version: 2.3.1dev
Summary: SQLAlchemy for NuoDB
Home-page: UNKNOWN
Author: Robert Buck
Author-email: buck.robert.j@gmail.com
License: MIT
Keywords: SQLAlchemy NuoDB
Platform: UNKNOWN
Classifier: Development Status :: 5 - Production/Stable
Classifier: Environment :: Console
Classifier: Intended Audience :: Developers
Classifier: License :: OSI Approved :: MIT License
Classifier: Operating System :: MacOS :: MacOS X
Classifier: Operating System :: POSIX :: Linux
Classifier: Programming Language :: Python
Classifier: Programming Language :: Python :: 2
Classifier: Programming Language :: Python :: 2.7
Classifier: Programming Language :: Python :: 3
Classifier: Programming Language :: Python :: 3.4
Classifier: Topic :: Database :: Front-Ends
